{
  "day": "3",
  "puzzles": [
    {
      "categories": [
        "Анатомы Италии",
        "Архитекторы Возрождения",
        "Баллистики",
        "Баснописцы",
        "Изобретатели Италии",
        "Инженеры Италии",
        "Космографы",
        "Механики XV века",
        "Механики XVI века",
        "Механики Италии",
        "Натурфилософы",
        "Ренессансные гуманисты",
        "Родившиеся 15 апреля",
        "Родившиеся в 1452 году",
        "Самоучки",
        "Умершие 2 мая",
        "Умершие в 1519 году",
        "Умершие в Амбуазе",
        "Учёные Эпохи Возрождения",
        "Физиологи Италии",
        "Художники Флоренции",
        "Художники итальянского Возрождения",
        "Художники мифологической тематики",
        "Художники-анатомы",
        "Художники-монументалисты Италии XV века",
        "Художники-монументалисты Италии XVI века",
        "Художники-портретисты Италии"
      ],
      "accept": [
        "092752ba56489644124d357d3af51daa74daa39635fd47d47c9016d19df65869",
        "44ebc4cbf8aed266039dc4bc427489a7c8414e8e737b5fd58bd2ddd152679361",
        "5a36b0948fb336a71b15b545c6d868426ab0807d03deddc432d34dd55aa45ec4",
        "86b452ffa15e0f9935f5af246892f24f7166e5f7fee060a7b9ad645567619de8",
        "afc352a18fb58e466772f61e42a8a862ac098829b05ca21b06e7c9235b6e483d"
      ],
      "reveal": "0JvQtdC+0L3QsNGA0LTQviDQtNCwINCS0LjQvdGH0Lg="
    },
    {
      "categories": [
        "Авторы детективной прозы",
        "Авторы исторических романов",
        "Авторы приключенческой литературы",
        "Английские писатели XIX века",
        "Английские писатели XX века",
        "Кавалеры ордена Короны Италии",
        "Кавалеры ордена Меджидие",
        "Масоны Шотландии",
        "Медики Шотландии",
        "Оккультисты",
        "Перезахороненные",
        "Писатели Великобритании XIX века",
        "Писатели Великобритании XX века",
        "Писатели Шотландии",
        "Писатели-фантасты Великобритании",
        "Похороненные в Великобритании",
        "Родившиеся 22 мая",
        "Родившиеся в 1859 году",
        "Родившиеся в Эдинбурге",
        "Рыцари-бакалавры",
        "Спиритуализм",
        "Умершие 7 июля",
        "Умершие в 1930 году",
        "Умершие в Кроуборо"
      ],
      "accept": [
        "156584f70e18b0a112a2f20bda7e4275ab594843ff82d65a0dc76dd1c56df0eb",
        "1b2801cce3f528db8091172324101159527212d39616a73234c7b383e30a6335",
        "1de6b321b36b24e5e8f43c0df5735d4e6d6660a391cd98bd0450860af4a84bbf",
        "bc5793c4e3c66ec83a2a33612facdea9fadb8e2e570f681adde227638b837457",
        "fa541cab7a0bee4a91faa7177496cd24b4f817881197283bfc4c432f645a5690"
      ],
      "reveal": "0JDRgNGC0YPRgCDQmtC+0L3QsNC9INCU0L7QudC7"
    },
    {
      "categories": [
        "Кинокомедии 1985 года",
        "Кинокомедии США",
        "Лауреаты мемориальной премии Джорджа Пала",
        "Национальный реестр фильмов",
        "Приключенческие фильмы США",
        "Работы, получившие премию «Хьюго» за лучшую постановку",
        "Фантастические комедии США",
        "Фантастические фильмы 1985 года",
        "Фильмы 1985 года",
        "Фильмы Amblin Entertainment",
        "Фильмы Роберта Земекиса",
        "Фильмы США 1985 года",
        "Фильмы на английском языке",
        "Фильмы по сценариям Боба Гейла",
        "Фильмы по сценариям Роберта Земекиса",
        "Фильмы с музыкой Алана Сильвестри",
        "Фильмы, адаптированные в телешоу",
        "Фильмы, спродюсированные Бобом Гейлом",
        "Фильмы, спродюсированные Нилом Кэнтоном"
      ],
      "accept": [
        "07cac875e7dd76ecb83cc76fc831068a5d86f21646a26f4fa88e09e5dc5b6ee8",
        "757120dd8bd065dcb668ad271ba85026d89f3ac5004ee69d36b2b9900cc3c27e"
      ],
      "reveal": "0J3QsNC30LDQtCDQsiDQsdGD0LTRg9GJ0LXQtQ=="
    },
    {
      "categories": [
        "Драматические телесериалы США",
        "Лауреаты премии «Эмми» за лучший драматический сериал",
        "Приключенческие телесериалы США",
        "Программы телеканала HBO",
        "Программы — лауреаты премии Пибоди",
        "Работы, получившие премию «Хьюго» за лучшую постановку (крупная форма)",
        "Семейные саги",
        "Смертная казнь в фильмах",
        "Телесериалы ЛГБТ-тематики США",
        "Телесериалы США в жанре фэнтези",
        "Телесериалы США, завершённые в 2019 году",
        "Телесериалы США, запущенные в 2011 году",
        "Телесериалы на английском языке",
        "Телесериалы о браке",
        "Телесериалы о братьях и сёстрах",
        "Телесериалы о ведьмах",
        "Телесериалы о демонах",
        "Телесериалы о дисфункциональных семьях",
        "Телесериалы о реинкарнации",
        "Телесериалы, основанные на романах",
        "Телесериалы, созданные Д. Б. Уайссом",
        "Телесериалы, созданные Дэвидом Бениоффом",
        "Телесериалы-лауреаты премии «Хьюго»",
        "Фильмы о близнецах",
        "Фильмы о домашнем насилии",
        "Фильмы о драконах",
        "Фильмы о жестоком обращении с детьми",
        "Фильмы о зомби",
        "Фильмы о пытках",
        "Фильмы об изнасиловании",
        "Фильмы об инцесте",
        "Экранизации произведений Джорджа Реймонда Ричарда Мартина",
        "Экшен-телесериалы США",
        "Эпические фильмы США"
      ],
      "accept": [
        "075f712246b1a9621ae9094449d63325166039d9fbab8d0ea969c7dcd71a266d",
        "ee5e7037741be88273ed0916ba02a7d91e76fd5a07caaf73c60921d244838ebd"
      ],
      "reveal": "0JjQs9GA0LAg0L/RgNC10YHRgtC+0LvQvtCyICjRgtC10LvQtdGB0LXRgNC40LDQuyk="
    },
    {
      "categories": [
        "3D-платформеры",
        "Головоломки от первого лица",
        "Игры для Linux",
        "Игры для PlayStation 3",
        "Игры для Windows",
        "Игры для Xbox 360",
        "Игры на движке Source",
        "Игры, использующие Havok",
        "Компьютерные игры 2011 года",
        "Компьютерные игры об искусственном интеллекте",
        "Компьютерные игры с женскими протагонистами",
        "Компьютерные игры с поддержкой кроссплатформенной игры",
        "Компьютерные игры — лауреаты D.I.C.E. Awards",
        "Компьютерные игры — лауреаты Golden Joystick Awards",
        "Компьютерные игры — лауреаты Steam Awards",
        "Компьютерные игры — лауреаты премии BAFTA Games",
        "Компьютерные игры, изданные «Букой»",
        "Компьютерные игры, разработанные Valve",
        "Компьютерные игры, разработанные в США",
        "Кооперативные компьютерные игры",
        "Многопользовательские и однопользовательские игры",
        "Продолжения компьютерных игр"
      ],
      "accept": [
        "4c36bfec2d3860125fe3d4b0718260176c2a5e7e38829756c20eb951b832224e"
      ],
      "reveal": "UG9ydGFsIDI="
    },
    {
      "categories": [
        "Исторические романы на русском языке",
        "Произведения, впервые опубликованные в журнале «Русский вестник»",
        "Романы 1869 года",
        "Романы Льва Толстого",
        "Романы о Москве",
        "Романы о Российской империи",
        "Романы о Санкт-Петербурге",
        "Романы-эпопеи",
        "Семейные саги"
      ],
      "accept": [
        "6b2e94912bb4d007b3a885a8ae5ecb90ee6c7f39d860ae97de881eab88fe077e",
        "abf23934097d57df62ec55b73086f1c36e4b7c8c268cf256cac0beefa3e84982"
      ],
      "reveal": "0JLQvtC50L3QsCDQuCDQvNC40YA="
    },
    {
      "categories": [
        "Абстракционизм",
        "Картины 1915 года",
        "Картины Казимира Малевича",
        "Картины из собраний Русского музея",
        "Картины из собраний Третьяковской галереи",
        "Картины из собраний Эрмитажа",
        "Произведения супрематизма"
      ],
      "accept": [
        "61743bfe75659a45e428afee15701f1bd6fa6cd9ea9f34e6ee966ed88cf2d59c",
        "f92e8c0574ed39cc325800f2687102e0fa40500a35c8acba15e38cb86cd28149"
      ],
      "reveal": "0KfRkdGA0L3Ri9C5INC60LLQsNC00YDQsNGC"
    },
    {
      "categories": [
        "Археоастрономия",
        "Всемирное наследие в Англии",
        "Исчезли во 2-м тысячелетии до н. э.",
        "Каменные круги",
        "Кромлехи",
        "Мегалиты Англии",
        "Появились во 2-м тысячелетии до н. э.",
        "Произведения 3-го тысячелетия до н. э.",
        "Уилтшир",
        "Хенджи"
      ],
      "accept": [
        "3f1abc38c459dead6b06a20296c56ec3a18f89b939a96ffda447333e490c1c3e",
        "a2d061827eec8b0790e4e718a629b5dfc971f77473b1a8a769bcea96981cbb33"
      ],
      "reveal": "0KHRgtC+0YPQvdGF0LXQvdC00LY="
    },
    {
      "categories": [
        "Июнь 1815 года",
        "События 18 июня",
        "Сражения 1815 года",
        "Сражения Брауншвейг-Люнебурга",
        "Сражения Великобритании",
        "Сражения Ганновера",
        "Сражения Наполеоновских войн",
        "Сражения Нассау",
        "Сражения Пруссии",
        "Сражения Франции",
        "Сражения в Бельгии"
      ],
      "accept": [
        "0b84bc7fe291ed79b38b653108dd5dc25a0fdbc58a1e4c1549c679017f827477",
        "838a470e73124106b0478ec591e1b2ff319e9aa9af9d303fecf766ff34d492fe",
        "e617f2f183d3b793e996397ce33d83a3c57aee0b4640fbe7cac4bda173be8672"
      ],
      "reveal": "0JHQuNGC0LLQsCDQv9GA0Lgg0JLQsNGC0LXRgNC70L7Qvg=="
    },
    {
      "categories": [
        "1977 год в космонавтике",
        "Автоматические межпланетные станции США",
        "Амальтея (спутник)",
        "Исследование Сатурна",
        "Исследование Юпитера",
        "Исследование гелиосферы",
        "Космические аппараты, покидающие Солнечную систему",
        "Энцелад (спутник)"
      ],
      "accept": [
        "535dd2db78cfeaefadc9272d68d1520b896dc66108e47e4cb596addd43e39bba",
        "b58f5299b535fc93a6bf19d557d325c5fdebc3e56c3af3ddf95e4bdee0461d7d"
      ],
      "reveal": "0JLQvtGP0LTQttC10YAtMQ=="
    }
  ]
}