{
  "day": "31",
  "puzzles": [
    {
      "categories": [
        "Биосферные резерваты Китая",
        "Высочайшие точки стран мира",
        "Гималаи",
        "Горные вершины Китая",
        "Горные вершины — восьмитысячники",
        "Горы Непала",
        "Горы Тибетского автономного района",
        "Крайние точки Азии",
        "Экстремальные точки Земли"
      ],
      "accept": [
        "0cbad8ea6b006354653f7b9105f00e24c13274122bffa8f17c1861f3f6686bfb",
        "0ea6d69edab594317e235cd9ccf4cd06a7a6b25ddd1abad91393cb1c77d2bfaf",
        "39e35ad8d3bcb9454d8569d5ec5e5a34e24c66f938668d556242dde1dfff3801",
        "76aea2801a6d8472e496bce7410ea1fda648b0b8c36323200a991c5cff7e1dd3",
        "fe598078658a01a34ce3110362ed653519b13cf4f67a4b55ba8d5d428121e72f"
      ],
      "reveal": "0JTQttC+0LzQvtC70YPQvdCz0LzQsA==",
      "difficulty": "medium"
    },
    {
      "categories": [
        "Анархисты Российской империи",
        "Анархисты Украины",
        "Бандиты",
        "Грабители",
        "Гражданская война в Одессе",
        "Персоналии:Одесса",
        "Преступники Российской империи",
        "Преступники, известные под псевдонимами",
        "Родившиеся 11 ноября",
        "Родившиеся в 1891 году",
        "Родившиеся в Одессе",
        "Умершие 4 августа",
        "Умершие в 1919 году",
        "Умершие в Вознесенске",
        "Участники Гражданской войны в России (красные)"
      ],
      "accept": [
        "417869105fc1828321b5b6d0862b988c6112b0ba4e4d730819d651431c74c0a6",
        "52354977aa3a657a7b78b9bdce2d18b2725e17e15bde4aff7c287f51012a2b14",
        "538b6e119df8bc840aed31daef6a9a108345191e9b6162f7c7bd675ef48d4dea",
        "73b01e752625b206207cc927b4b5062131736ecaeb04efeef5955423e6185980",
        "7a99b0c70ad50630bea6c9192e2585e3c90bde7495ac0b2e799b3ab3ebd01b7d",
        "9696926df5752f620da4190ad08add11217c0f1b5be4527350196062031f3cca",
        "a0d0eb7ae1de7afc66185370efee97106296df8bb6c365434c219ac8b4ea3ed9",
        "a8ebc669e49399e805e377d3248629d272d4049876c94286cc892bcab7c07c24",
        "acd0cd7be73b9c7f08972c43c82e2f3dce4d6096f6ffaf7de80d77c4c8ec2993",
        "b6d6ae93ef576307c183b0f6631d7d2119cb17937b6d9458d2b3c8594dd04e63"
      ],
      "reveal": "0JzQuNGI0LrQsCDQr9C/0L7QvdGH0LjQug==",
      "difficulty": "medium"
    },
    {
      "categories": [
        "Заслуженные мастера спорта России",
        "Игроки ФК 2DROTS",
        "Игроки ФК «Антальяспор»",
        "Игроки ФК «Ахмат»",
        "Игроки ФК «Истанбул Башакшехир»",
        "Игроки ФК «Краснодар»",
        "Игроки ФК «Ростов»",
        "Игроки ФК «Рубин»",
        "Игроки ФК «Сибиряк»",
        "Игроки ФК «Сочи»",
        "Игроки ФК «Спартак» Москва",
        "Игроки ФК «Томь»",
        "Игроки ФК «Факел» Воронеж",
        "Игроки ФК «Химки»",
        "Игроки сборной России по футболу",
        "Игроки сборной России по футболу (до 21 года)",
        "Награждённые Почётной грамотой Президента Российской Федерации",
        "Родившиеся 5 апреля",
        "Родившиеся в 1987 году",
        "Родившиеся в Бодайбинском районе",
        "Футболисты России"
      ],
      "accept": [
        "0b99c3c9e2a31ba42878444398e7283e1681c3c13d7c725fd6027c8ecc37f10d",
        "37db9c12b8dda4d33c5ff2a07d77351d8c206cbed35905fb52b638332852d08a",
        "5ef40c5b2e9fa680fbdf9d55fc810573e1166e74fd23089859defe71e5d1d1db",
        "b41e9498a2b1c09fc3f4ace359041768d7b870b0db86bc47c5716c9efd8d3bcc",
        "d74547112fc1d7a2a5c070b5b58e4c44dfd9efb3c9de54018357224819d4629b"
      ],
      "reveal": "0JrRg9C00YDRj9GI0L7Qsiwg0KTRkdC00L7RgCDQktCw0YHQuNC70YzQtdCy0LjRhw==",
      "difficulty": "easy"
    },
    {
      "categories": [
        "Государства НАТО",
        "Государства — члены ООН",
        "Страны у Адриатического моря",
        "Унитарные республики"
      ],
      "accept": [
        "854455593920cc0e2c40f63aa53bd7a1f50f7e6e5079c63f251fb39b25ea44f7",
        "c3780f916172153ec2548eda1edc5072e89f3fa66bbc34f0d60ebe110b0c2e40",
        "e31ac84ad71e5071be895000c93eecb68df7d30167e1f921c2bb45938a89f4d4",
        "e83f024f9a1156e097a79f6010bd852c1aae61e4dd9ad12a00be42d1bf457466"
      ],
      "reveal": "0JDQu9Cx0LDQvdC40Y8=",
      "difficulty": "hard"
    },
    {
      "categories": [
        "Выборгские губернаторы",
        "Выпускники Артиллерийской и Инженерной шляхетской школы",
        "Генерал-фельдмаршалы (Российская империя)",
        "Главы Санкт-Петербурга",
        "Директора Первого кадетского корпуса",
        "Инвалиды военных конфликтов (Российская империя)",
        "Исторические персонажи романа «Война и мир»",
        "Кавалеры Большого креста Военного ордена Марии Терезии",
        "Кавалеры золотого оружия «За храбрость» с бриллиантами",
        "Кавалеры ордена Красного орла 1 степени",
        "Кавалеры ордена Святого Александра Невского",
        "Кавалеры ордена Святого Владимира 1-й степени",
        "Кавалеры ордена Святого Владимира 2-й степени",
        "Кавалеры ордена Святого Георгия I класса",
        "Кавалеры ордена Святого Георгия II класса",
        "Кавалеры ордена Святого Георгия III класса",
        "Кавалеры ордена Святого Георгия IV класса",
        "Кавалеры ордена Святого Иоанна Иерусалимского",
        "Кавалеры ордена Святого апостола Андрея Первозванного с алмазами",
        "Кавалеры ордена Святой Анны 1-й степени",
        "Кавалеры ордена Чёрного орла",
        "Литовские генерал-губернаторы",
        "Масоны России",
        "Памятник «Тысячелетие России»",
        "Послы Российской империи в Османской империи",
        "Похороненные в Санкт-Петербурге",
        "Похороненные в соборах",
        "Родившиеся 16 сентября",
        "Родившиеся в 1747 году",
        "Родившиеся в Новгородской губернии",
        "Родившиеся в Санкт-Петербурге",
        "Российские командиры Наполеоновских и Революционных войн",
        "Санкт-Петербургские генерал-губернаторы",
        "Светлейшие князья",
        "Умершие 28 апреля",
        "Умершие в 1813 году",
        "Умершие в Болеславце",
        "Участники Бородинского сражения",
        "Участники Кинбурнской баталии (1787)",
        "Участники Отечественной войны 1812 года",
        "Участники Русско-польской войны 1792 года",
        "Участники Русско-турецкой войны (1768—1774)",
        "Участники Русско-турецкой войны (1787—1791)",
        "Участники Русско-турецкой войны (1806—1812)",
        "Участники осады Бендер (1770)",
        "Участники осады Бендер (1789)",
        "Участники осады и штурма Очакова (1788)",
        "Участники сражения под Малоярославцем",
        "Участники штурма Измаила (1790)",
        "Члены Государственного совета Российской империи"
      ],
      "accept": [
        "01cd591b222e009be84bb187aa056c908e2c5263a6fb6f31936d7cdfc3b2c6f6",
        "02c7170d73dac184a2bc5f016565eb46c38604e18317dbd9a06b1341cab5b5e0",
        "0c2a55f517338f2270ee5eec8d5cbe0a5ffd8ae20c22e7e812cff00594188653",
        "347ebc738ebcd57bf70c70ce03cbc12139d60b104269153d100d31b19710124d",
        "4933fb79b014778795d1b37cf9af7930b23a4659abed26d6a42d80a90cb215a8",
        "5c4b86f1afc1ac8092cded7b2782d6297442b1b30f3ad99295d8e16be97900be",
        "6319371b68be7e218f2a152895c86b4301bd379c196fb019bcbb92edc7ce8095",
        "9c47dc1a93512aadee5925f5bf20d353367a147f782d54dbf536df251f031b05",
        "aff0fb9f665c2c38e3765f052e27098d289b19b1b8767d5921fff3d98c2361b1",
        "d517998d9893a6546b17ec2426f8d41ee82284938c32ed0b0720dbe628c8ec5a",
        "f5955768fc5afd36dfbd23858767da944a53b1e7d420d178263187cf5c271f31"
      ],
      "reveal": "0JrRg9GC0YPQt9C+0LIsINCc0LjRhdCw0LjQuyDQmNC70LvQsNGA0LjQvtC90L7QstC40Yc=",
      "difficulty": "easy"
    },
    {
      "categories": [
        "Близнечные мифы",
        "Боги медицины и здоровья",
        "Гомоэротические мотивы в древнегреческой мифологии",
        "Двенадцать богов Олимпа",
        "Древнегреческие боги",
        "Метафоры",
        "Мифологические лучники",
        "Мифы о Гермесе",
        "Персонажи «Одиссеи»",
        "Солярные боги"
      ],
      "accept": [
        "058b4d8e5409d96757d48207855aedb42f96ab4d2c0cf03349f28c0059381a65",
        "1acae075f63b5a5016daf786689b1f5adc51e2de2b15817888d66cf0d26e1393",
        "5fb399ff6d1e27cf8540b8e43a1e1b2992bfe2a788cbc1203bcf86683f346842",
        "748d66ad16327f96ce4ebee37adb89b543d6193d7bbdd424c52a753050ef9c47",
        "a4de68667b226ba0387d81b6db6f78e8279fe40182cd82cae2f6a16173185964",
        "aeb1f756924642d6ef5a631afe64285ed330f139ffa1e4c3cc7e848d2ad84545",
        "ccef18bfff340ccc996bfa6733c23b1164dc9b7f007c1e5c313589f96d001931",
        "e95f332591cb502fda6c1651c11a567b7cafede219bdaf8f4e54c779cac6876c"
      ],
      "reveal": "0JDQv9C+0LvQu9C+0L0=",
      "difficulty": "medium"
    },
    {
      "categories": [
        "Интернет-мемы, связанные со вторжением России на Украину",
        "Пропаганда в России во время вторжения на Украину (с 2022)",
        "Цензура в России во время вторжения на Украину",
        "Эвфемизмы"
      ],
      "accept": [
        "51b02f51c3a8935f573eca88cadf97c147f2e920e85205c51cfc3050f1b1e33a",
        "561a827aa491bec6bf103ad6cc32be04f4af9d44df69fb455551ff61cfdc9350",
        "a7a056df18dbe6c4635dcede90fb28b337eb6e51b6a0f430641de09408adec32",
        "b58dfc631be3c33f702ca299ee8f0d79437d26bc0dff3e8d0a406f2962c30840",
        "bace64c252a704c5968f4f5e23e9f47f0989544b391ce30ade60031b48ae08fc",
        "c668e4d086e929406c092de218213c2149c6cb5e6f5787d216c61b0a3f702268",
        "dfaf44902c7e7833fcd3ee2db3f18c0cf88b6a7b78feeb7d947c0544e725383f"
      ],
      "reveal": "0KHQv9C10YbQuNCw0LvRjNC90LDRjyDQstC+0LXQvdC90LDRjyDQvtC/0LXRgNCw0YbQuNGP",
      "difficulty": "hard"
    },
    {
      "categories": [
        "Великие князья киевские",
        "Военачальники Северо-Восточной Руси",
        "Князья ростовские",
        "Мономаховичи",
        "Основатели городов",
        "Отравленные",
        "Персоналии:Суздаль",
        "Похороненные в Церкви Спаса на Берестове",
        "Родившиеся в 1090-е годы",
        "Умершие 15 мая",
        "Умершие в 1157 году",
        "Умершие в Киеве"
      ],
      "accept": [
        "2f7de79a9478b0f3a28bf4a66e8528847865657741be308338129486bce147bd",
        "512cd7c5d6b28afbe889424ceba5fde67807dc5952ab15b76405358c5d764e58",
        "70e0fcb39f741ff9deeb81dc157dedbdfcf910315fbc2c45e3364e662563fe17",
        "7a02e5b9728140e4a402958667d740b53acb6400708f1e0d09a9c5f6a1cf99ac",
        "92272d4d569926d7eb1be506ca70556c94480cc8012db3738e8fc8b2d1c8fe37",
        "b39ec09b7987ea61b9f3486784405ec3a4f6a003f68418debfb0bd7dc142b41e",
        "b9047e57ac3d294c1b305b80e850b3c70db6cca1d5f5ce6eeb444a14486c4699",
        "b9234274cb60f763e755bd58fd2eacb8b75311bd16e1cb9641e30b498dc0fda9",
        "c574c7a3ad657a813a4307b8863a809b5769c0a24c66046b0f870a2912589d5c",
        "d60f2f694f9efbba76116d9c3cc9ce6aa993df02be2814616e572708ab3ad543",
        "d7f34b1720e01f62c4d32583a658f2da720bb4d41a39a2bf4b55a4c7f1bb81a9",
        "e0ffe745f6e8e330254ed8d8a73f57c6edb53a836490b4530ebda2d1c29cbaca",
        "ffd1b8f71ffe481950472a63d25603cd877ccb7f78da1cc89f650bf4b1fcca13"
      ],
      "reveal": "0K7RgNC40Lkg0JLQu9Cw0LTQuNC80LjRgNC+0LLQuNGHINCU0L7Qu9Cz0L7RgNGD0LrQuNC5",
      "difficulty": "medium"
    },
    {
      "categories": [
        "Бронзовые призёры летних Олимпийских игр 2000 года",
        "Выпускники Российского государственного университета туризма и сервиса",
        "Выпускники Университета имени Лесгафта",
        "Гимнастки (художественная гимнастика) России",
        "Гимнасты на летних Олимпийских играх 2000 года",
        "Гимнасты на летних Олимпийских играх 2004 года",
        "Гимнасты, дисквалифицированные за нарушение антидопинговых правил",
        "Депутаты Государственной думы Российской Федерации V созыва",
        "Депутаты Государственной думы Российской Федерации VI созыва",
        "Женщины-политики России",
        "Заслуженные мастера спорта России",
        "Кавалеры ордена «За заслуги перед Отечеством» 4-й степени",
        "Кавалеры ордена Дружбы (Россия)",
        "Кавалеры ордена Почёта (Южная Осетия)",
        "Кандидаты педагогических наук",
        "Лица, подвергнутые санкциям со стороны Великобритании в связи с российско-украинской войной",
        "Лица, подвергнутые санкциям со стороны ЕС в связи с российско-украинской войной",
        "Лица, подвергнутые санкциям со стороны Канады в связи с российско-украинской войной",
        "Медиаменеджеры",
        "Награждённые Почётной грамотой Президента Российской Федерации",
        "Национальная Медиа Группа",
        "Окружение Владимира Путина",
        "Олимпийские чемпионки по художественной гимнастике",
        "Олимпийские чемпионы от России",
        "Родившиеся 12 мая",
        "Родившиеся в 1983 году",
        "Родившиеся в Ташкенте",
        "Чемпионки Европы по художественной гимнастике",
        "Чемпионки мира по художественной гимнастике",
        "Чемпионы летних Олимпийских игр 2004 года",
        "Члены «Единой России»",
        "Члены Общественной палаты России (2006—2008)"
      ],
      "accept": [
        "06b2c5dff1926cd3e606dfb67153b36adf2846117dfad1e3db7b7601d0656307",
        "2058b6dfecceb04ceea05a2aebfe709f11464eb2336b9419a2b096b916598bf6",
        "54e4a6fbdeac0d83cae22fe010069c2b10a153c71c9434b1a52bbabd8bba68ed",
        "8bbbdd86f31918ea7beb5462d681f6aa66ea77b9e21954eb59c81087db50077f",
        "93e52a6de39de9e739f2656228296e54ceda2a22beeb725a67c9c234796554cf",
        "d3d0a169b899738a72d351715c7c9e01bb0c0ca873e43cc6460d270e4aa68cfe",
        "f7250e7473b5875343aa4b462f94fd8aecad128a6df46e19c739c6fef14c4f27"
      ],
      "reveal": "0JrQsNCx0LDQtdCy0LAsINCQ0LvQuNC90LAg0JzQsNGA0LDRgtC+0LLQvdCw",
      "difficulty": "easy"
    },
    {
      "categories": [
        "Выпускники Армянского института физической культуры",
        "Родившиеся 5 июля",
        "Родившиеся в 1957 году",
        "Родившиеся в Тбилиси",
        "Тренеры России по фигурному катанию",
        "Тренеры США по фигурному катанию",
        "Фигуристы СССР"
      ],
      "accept": [
        "08c34bf626c70c387e86be29a88ec1a41394e0265dfd8ba9dd73c1d28aa8cbbd",
        "19f1d8c02d52eda5641a4981ec7f5033d2d83a5888a60298045f0f8226ff4878",
        "1abb00329e87505da6cd70a83141464bb93c584713f5d80e849e68f6be8885ef",
        "4eea15a8431563b50e3c91d7937aa972f69a6d7731eb3a43246ebe0684d70c4b",
        "c8e59ea847f9f9498d099a6a0d19e3ecdd14b78d030b9d5ac6852a59d38b8df1"
      ],
      "reveal": "0JDRgNGD0YLRjtC90Y/QvSwg0KDQsNGE0LDRjdC70Ywg0JLQu9Cw0LTQuNC80LjRgNC+0LLQuNGH",
      "difficulty": "hard"
    }
  ]
}