{
  "day": "45",
  "puzzles": [
    {
      "categories": [
        "Законодательство XVIII века",
        "Исторические конституции",
        "История права Беларуси",
        "Конституции Польши",
        "Конституционное право Литвы",
        "Литовско-польские отношения",
        "Право Речи Посполитой"
      ],
      "accept": [
        "15d590c7a813b594f55de1373ad7b7a74140b2def96939c9095d76d387bdc4d0",
        "15ec96c6d30d5626bb4e1f1f514e8d4984ca727786e8910e436e7dbada8bd36d",
        "462d1d1f1dd2f402404d9a88f3225be21ec7161990a71488463ebdeb874cd3b1",
        "474c885a0b181b3a9c9c377e01aff100179887c94b5ad4d50bb885c8e723182b",
        "84219214386dcdab217ad104e3559e1b386fa3fcd90e3fcc22f73d40f8ed8da5",
        "8f974bf3692b420a65dad947913f60ef9486b28575b002e5d2af2f32a0d65de1",
        "8fe98e0401dfc5f8f971c15acd0ba76b2d5ca45112e985f30ed3b9fb4ea9763c",
        "9b11049a5a19e9359a52d2e2142dc2b57c04f2de27f11fbddf40c046483e0560",
        "9d3ec07696df4580fda079a9e59376aee7c77a1d0f42f46cce170362f49798ce",
        "adbde556f2ee4c80f9ce89612ae85625ad892e3501c4d39c759c1054e400f805",
        "c1260cbcd21272ee7877914e710e825c138f26f6a81f456a8b069de0d4a1e48e"
      ],
      "reveal": "0JrQvtC90YHRgtC40YLRg9GG0LjRjyAzINC80LDRjyAxNzkxINCz0L7QtNCw",
      "difficulty": "medium"
    },
    {
      "categories": [
        "Знаменосцы на летних Олимпийских играх 2004 года",
        "Знаменосцы на летних Олимпийских играх 2008 года",
        "Обладатели Кубка Дэвиса",
        "Олимпийские чемпионы от Швейцарии",
        "Олимпийские чемпионы по теннису",
        "Первые ракетки мира (мужчины)",
        "Победители Открытого чемпионата Австралии по теннису в мужском одиночном разряде",
        "Победители Открытого чемпионата США по теннису в мужском одиночном разряде",
        "Победители Открытого чемпионата Франции по теннису в мужском одиночном разряде",
        "Победители Уимблдонского турнира в мужском одиночном разряде",
        "Победители Уимблдонского турнира в одиночном разряде среди юношей",
        "Победители Уимблдонского турнира в парном разряде среди юношей",
        "Послы доброй воли ЮНИСЕФ",
        "Почётные доктора Базельского университета",
        "Родившиеся 8 августа",
        "Родившиеся в 1981 году",
        "Родившиеся в Базеле",
        "Серебряные призёры летних Олимпийских игр 2012 года",
        "Теннисисты на летних Олимпийских играх 2000 года",
        "Теннисисты на летних Олимпийских играх 2004 года",
        "Теннисисты на летних Олимпийских играх 2008 года",
        "Теннисисты на летних Олимпийских играх 2012 года",
        "Чемпионы летних Олимпийских игр 2008 года"
      ],
      "accept": [
        "24953a0773ef3dfe6ff4409da22bb60ac9889d06e83485ed2663baade98c0407",
        "350a85e92caaf25307157b8f7db4d5efba28e79b042597f66dbb0afd8fd1331d",
        "5301cfd32d73b4774444a3493ab16abd3a4e8e9f1fe5a8a8c71b25488421e339",
        "8d69b506de2b47a925516ef111588a0cb9c546e48feadd4b6914df5025088697",
        "a53a30be6bfb73b6c301136cfc23e0a64e15f4bfa0c2e01bd70005866421baaf",
        "b940c12e939c0e9771d95b69473d9dcd3511f851f5f901e5a690c6e071bddb04"
      ],
      "reveal": "0KDQvtC00LbQtdGAINCk0LXQtNC10YDQtdGA",
      "difficulty": "easy"
    },
    {
      "categories": [
        "Военачальники Александра Македонского",
        "Правители Азии IV века до н. э.",
        "Сатрапы Бактрии",
        "Сатрапы Согдианы",
        "Сатрапы империи Александра Македонского",
        "Умершие в 328 году до н. э.",
        "Умершие в Самарканде"
      ],
      "accept": [
        "02768bba107a2fc9aae9d30d38dbe69d268cfa0593af026cb620df264e1f0af7",
        "3b65e415bad267e2df0fc3e463a62bd2de77bf0b76fe8a6147c76f0c4576c59e",
        "6a3c870d25ab3e4adedee6c135dd55ebfdc0128f0a0349f59d34d7019c7d547c",
        "c006c7e3ab14d686f63524136f1ec7c5e553d839bc01c851e4dc9de2bdbfc589",
        "db42cf05e665271fa3c346e94929b33bbf5be66b0c29beea679b31d02e2864eb"
      ],
      "reveal": "0JrQu9C40YIg0KfRkdGA0L3Ri9C5",
      "difficulty": "medium"
    },
    {
      "categories": [
        "Ацилии",
        "Военачальники Древнего Рима",
        "Децемвиры",
        "Народные трибуны",
        "Преторы",
        "Римские консулы II века до н. э.",
        "Эдилы"
      ],
      "accept": [
        "47785bd27ac2bb499164e0966310b94f9aea1ddee025cf3ce39b216bb56e4b83",
        "a58585e0b9b67c09a475a307165cc899fb040cb80de26a1292fe2fde5b342809"
      ],
      "reveal": "0JzQsNC90LjQuSDQkNGG0LjQu9C40Lkg0JPQu9Cw0LHRgNC40L7QvSAo0LrQvtC90YHRg9C7IDE5MSDQs9C+0LTQsCDQtNC+INC9LiDRjS4p",
      "difficulty": "hard"
    },
    {
      "categories": [
        "Бронзовые призёры зимних Олимпийских игр 1972 года",
        "Выпускники Московского пограничного института ФСБ России",
        "Выпускники Смоленского государственного университета спорта",
        "Заслуженные мастера спорта СССР",
        "Знаменосцы на зимних Олимпийских играх 1972 года",
        "Кавалеры ордена Александра Невского (Российская Федерация)",
        "Кавалеры ордена Ленина",
        "Кавалеры ордена Трудового Красного Знамени",
        "Лыжники СССР",
        "Лыжники на зимних Олимпийских играх 1968 года",
        "Лыжники на зимних Олимпийских играх 1972 года",
        "Награждённые медалью «За трудовое отличие»",
        "Олимпийские чемпионы от СССР",
        "Олимпийские чемпионы по лыжным гонкам",
        "Подполковники (СССР)",
        "Похороненные в Тульской области",
        "Почётные граждане Тульской области",
        "Родившиеся 1 октября",
        "Родившиеся в 1941 году",
        "Родившиеся в Дубенском районе (Тульская область)",
        "Серебряные призёры зимних Олимпийских игр 1968 года",
        "Умершие 22 октября",
        "Умершие в 2021 году",
        "Умершие в Москве",
        "Чемпионы СССР по лыжным гонкам",
        "Чемпионы зимних Олимпийских игр 1972 года",
        "Чемпионы мира по лыжным гонкам",
        "Члены КПСС"
      ],
      "accept": [
        "8269f00d3e8f5a044edf5771d3ab096bd6d1aa115fd95b563e3d8cea43fb5616",
        "ae84331dab7611f5a2f4bbb4727cf0578221f7bc357f0a0e0e7529056e4f0168",
        "ea650b7bacfd58499951c22063d2f8027f8aa7fa40d2261d0f63ff64293bad8e",
        "ef6580418be2c5df51c3d0893e505a2654eb5dd00e8797220e0f858ae21aa10a",
        "f4290f4b273f9454ef4fd09a1b8c6a1ec6a5a42567a73a303405e48c266aa373"
      ],
      "reveal": "0JLQtdC00LXQvdC40L0sINCS0Y/Rh9C10YHQu9Cw0LIg0J/QtdGC0YDQvtCy0LjRhw==",
      "difficulty": "easy"
    },
    {
      "categories": [
        "Виды вне опасности",
        "Кормовые растения",
        "Кормовые растения европейского лося",
        "Кормовые растения северного оленя",
        "Осоковые",
        "Растения болот",
        "Растения, впервые описанные в книге Species Plantarum",
        "Флора Евразии",
        "Флора Северной Америки"
      ],
      "accept": [
        "1904fced41bcb3f71e80a7a73debed9a234ff990fd27b067cba69ea0a4d43e5d",
        "1c8f8806f4fded8d36867fc60ee0afd91a1fffd9312beb2a5ecef828257fb300",
        "2487baf6253937b0a965b705c87f804c409290336300e02a9b95fca972ddf915",
        "3b9a16a639486d2597923c754ec5603ab07426a904d3a2cfaaf15661677d4ed2",
        "3bc74041b77492a389f6693b665f26661e735c42844843dea26b3b55e5397a72",
        "57ad28f5f6676d3f9b06f7324d03936f34ca06abc0fbf8fe766d03d7444893b4",
        "6272ec480ea46d4e6efeebea059bc339534d38afccbbb7d04cbde703d64349e0",
        "727c5aa2917f5cc3f4c696fef437ce84c360dace1c48df31ece480958a29305a",
        "832837bbf3c4bc42e645bd118819122625fee4347d7157c9029653af86882522",
        "89e406a4f9ce29e69b48e1a1cf5beb578883f96032e405ae3b09ef12aa8a8ba2",
        "b39139963da32600597638c6239243eaccf29ed9a8488ff0a862fc567a2921f8",
        "ba9b45895ba6af2ba6f8500d9f315f4fc8d4d95de5f1b56f7917993ca9a16f6f",
        "c5043b0885da43c8230f021ebba51b6524480559ef5afc64820a7f0a0c30ea73",
        "ccd183c5679f8f0f2eea5ce231db0c8aa8eb92aa1681091a090aee170a1ce0cc",
        "f39003a3438ab0284877b621e3e406d3061f097fc45f9406f1b6d22fc67863cb"
      ],
      "reveal": "0J/Rg9GI0LjRhtCwINCy0LvQsNCz0LDQu9C40YnQvdCw0Y8=",
      "difficulty": "medium"
    },
    {
      "categories": [
        "Бофорты",
        "Ланкастеры",
        "Похороненные в Кентерберийском соборе",
        "Умершие 31 декабря",
        "Умершие в 1439 году",
        "Умершие в Лондоне"
      ],
      "accept": [
        "4cf76007b7e3a36356661b1b22d71a66618582f64a229fc4fcf3cfc9b83c707a",
        "64e4a7578fb0c7b81c6e93d631aef94266000b85e80d079b7ad606e95da49099",
        "c8f2ca65f44969409af3b067a9d0ec1451ae4121a83c3f86a79424884251417b",
        "dcbac613276f15351dc3d44904995256cc456b25ff39cde9494456f0151f9cd4",
        "fe18ec44f139d49fdbac6971edbb0080995996c95ee502c00d0c879acf78116d"
      ],
      "reveal": "0KXQvtC70LvQsNC90LQsINCc0LDRgNCz0LDRgNC10YI=",
      "difficulty": "hard"
    },
    {
      "categories": [
        "Арменисты",
        "Востоковеды Российской империи",
        "Действительные члены Петербургской академии наук",
        "Историки Российской империи",
        "Историки Франции",
        "Кавалеры ордена Святого Владимира 3-й степени",
        "Кавалеры ордена Святого Станислава 1-й степени",
        "Кавалеры ордена Святой Анны 1-й степени с императорской короной",
        "Кавалеры ордена Святой Анны 2-й степени",
        "Кавалеры ордена Святой Анны 3-й степени",
        "Картвелологи",
        "Лингвисты XIX века",
        "Персоналии:Государственный Эрмитаж",
        "Похороненные во Франции",
        "Родившиеся 5 февраля",
        "Родившиеся в 1802 году",
        "Родившиеся в Париже",
        "Сотрудники Российской национальной библиотеки",
        "Тайные советники",
        "Умершие 3 сентября",
        "Умершие в 1880 году",
        "Умершие в департаменте Вьенна",
        "Филологи Франции",
        "Члены Прусской академии наук"
      ],
      "accept": [
        "0efefc87ac5403165f00e3219371bbabaaa432d420c764abf37ff7b35f42f747",
        "239ebd50fbe9eb4c597dea54764200911b49f7dab4b32a0908c3682a804fe2d2",
        "336431df32560e94b2b6233a7dd50aecabb4e215ec377b3f1a337e0237d34bf4",
        "62ad54f6bb380ee034b2856f7484d4ba52a453a2215b2334ff8efb76aae67d93",
        "9510555f92ba7e9347c68e4571ba3a8695560aed5ab0fba7c4e1d1d030549e60",
        "ab66435df8e7d38ed0044664292062f82d73c1780a11f966bca5457e9921c65a"
      ],
      "reveal": "0JHRgNC+0YHRgdC1LCDQnNCw0YDQuNC5INCY0LLQsNC90L7QstC40Yc=",
      "difficulty": "easy"
    },
    {
      "categories": [
        "Богословы Византии",
        "Платоники эпохи Возрождения",
        "Родившиеся в XIV веке",
        "Родившиеся в Стамбуле",
        "Умершие 26 июня",
        "Умершие в 1452 году",
        "Философы XV века",
        "Философы Византии",
        "Христианские богословы"
      ],
      "accept": [
        "3339ab1a9bf0008973ea1de3d7903967ca803e59748a0a9424027320989702c3",
        "43f82919dc566b29e816aa64a9c73e60f44d73aac92f4100d51c98b9b6976afc",
        "7580122c98210eb12bcdf04214c5fea05906c67b93e28acde257112781aac980",
        "9f9e4ca661c9433b58424da595372ee97afbb88b0a1c186fec4da07c62c13e92",
        "a3890d813e76ec3c82bad5285036214a5c053bc60b5fc2a420648d60a04359ca",
        "b941c30ad20a0f91d98b8497ebd01c23765dcc55038c426109e7465c6f6171c1",
        "cbf9a137f11109eb43cd7d807861a6ce391a84ac70d6948b81cff5d94943e577"
      ],
      "reveal": "0J/Qu9C40YTQvtC9",
      "difficulty": "medium"
    },
    {
      "categories": [
        "Иркутская агломерация",
        "Населённые пункты Иркутского района",
        "Населённые пункты Марковского муниципального образования",
        "Населённые пункты на Ангаре",
        "Населённые пункты, основанные в 1953 году"
      ],
      "accept": [
        "9a63bcee49562a3acdd0d84b9fdd8bf0f4ac7527e94618d53af0053e8408f711",
        "dea759f01bac60df569068a3c9505a2f65d7bcfbac2f324f79a574d69e316ff4"
      ],
      "reveal": "0J3QvtCy0L7Qs9GA0YPQtNC40L3QuNC90LA=",
      "difficulty": "hard"
    }
  ]
}